[
  {
    "id": 1, 
    "titolo": "Bio Punk",
    "autore": "Kobose",
    "modulo_corso": "Modulo III: Proiezione e Mercato",
    "tono_voce": "Aggressivo",
    "tema": "Fantascienza e Tecnologia/Rilegatura Finale",
    "anno": 2025,
    "numero_pagine": 16, 
    "link_fanzine": "assets/bio-punk_kobose_20p_spread.pdf",
    "link_copertina": "assets/bio-punk_kobose_cover.jpg" 
  },
  {
    "id": 2, 
    "titolo": "Brutalist",
    "autore": "Kobose",
    "modulo_corso": "Modulo II: Mani, Macchine & Layout",
    "tono_voce": "Aggressivo",
    "tema": "Design Brutalista e Tipografia",
    "anno": 2025,
    "numero_pagine": 24, 
    "link_fanzine": "assets/Brutalist_kobose.pdf",
    "link_copertina": "assets/Brutalist_kobose_cover.jpg" 
  },
  {
    "id": 3, 
    "titolo": "Far-Fest",
    "autore": "Kobose",
    "modulo_corso": "Modulo I: Lo Sguardo e la Strategia",
    "tono_voce": "Poetico",
    "tema": "Preistoria e Western/Visione Critica",
    "anno": 2025,
    "numero_pagine": 32, 
    "link_fanzine": "assets/Far-Fest_kobose_zine_32p-web.pdf",
    "link_copertina": "assets/Far-Fest_kobose_cover.jpg" 
  },
  {
    "id": 4, 
    "titolo": "Bull",
    "autore": "Kobose",
    "modulo_corso": "Modulo III: Proiezione e Mercato",
    "tono_voce": "Aggressivo",
    "tema": "Cut-Up e Guerriglia Visiva",
    "anno": 2025,
    "numero_pagine": 28, 
    "link_fanzine": "assets/Bull_kobose_24p_spread-w.pdf",  
    "link_copertina": "assets/Bull_kobose_cover.jpg" 
  }
]
